django_alpine/__init__.py
django_alpine/apps.py
django_alpine/static/js/alpine.js
django_alpine/templatetags/__init__.py
django_alpine/templatetags/alpine_tags.py
django_alpine-0.1.4.dist-info/LICENSE
django_alpine-0.1.4.dist-info/METADATA
django_alpine-0.1.4.dist-info/WHEEL
django_alpine-0.1.4.dist-info/top_level.txt
django_alpine-0.1.4.dist-info/RECORD
