Metadata-Version: 2.1
Name: django-alpine
Version: 0.1.4
Summary: A Django package to include alpine.js to your django project.
Home-page: https://github.com/ProKelly/django-alpine.git
Author: Anye Prince Kelly
Author-email: Anye Prince Kelly <firstanye@gmail.com>
Maintainer-email: Anye Prince Kelly <firstanye@gmail.com>
Project-URL: Repository, https://github.com/ProKelly/django-alpine.git
Classifier: Environment :: Web Environment
Classifier: Framework :: Django
Classifier: Framework :: Django :: 4.2
Classifier: Intended Audience :: Developers
Classifier: License :: OSI Approved :: BSD License
Classifier: Operating System :: OS Independent
Classifier: Programming Language :: Python
Classifier: Programming Language :: Python :: 3
Classifier: Programming Language :: Python :: 3 :: Only
Classifier: Programming Language :: Python :: 3.10
Classifier: Programming Language :: Python :: 3.11
Classifier: Programming Language :: Python :: 3.12
Classifier: Programming Language :: Python :: 3.13
Classifier: Topic :: Internet :: WWW/HTTP
Classifier: Topic :: Internet :: WWW/HTTP :: Dynamic Content
Requires-Python: >=3.10
License-File: LICENSE
Requires-Dist: django>=4.2
Requires-Dist: requests>=2.25
